dungeon_master/__init__.py
dungeon_master/dm.py
dungeon_master-0.0.1.dist-info/LICENSE
dungeon_master-0.0.1.dist-info/METADATA
dungeon_master-0.0.1.dist-info/WHEEL
dungeon_master-0.0.1.dist-info/top_level.txt
dungeon_master-0.0.1.dist-info/RECORD
